MANIFEST.in
README.rst
distribute_setup.py
setup.py
django_jira_oauth.egg-info/PKG-INFO
django_jira_oauth.egg-info/SOURCES.txt
django_jira_oauth.egg-info/dependency_links.txt
django_jira_oauth.egg-info/requires.txt
django_jira_oauth.egg-info/top_level.txt
jira_oauth/__init__.py
jira_oauth/decorators.py
jira_oauth/urls.py
jira_oauth/views.py