Metadata-Version: 1.1
Name: django-jira-oauth
Version: 0.1.2
Summary: OAuth authentication with JIRA from Django
Home-page: https://github.com/MicahCarrick/django-jira-oauth
Author: Micah Carrick
Author-email: micah@quixotix.com
License: UNKNOWN
Platform: UNKNOWN
Classifier: Development Status :: 4 - Beta
Classifier: Environment :: Console
Classifier: Intended Audience :: Developers
Classifier: Operating System :: OS Independent
Classifier: Programming Language :: Python
Classifier: Topic :: Software Development :: Libraries :: Python Modules
Classifier: Topic :: Internet :: WWW/HTTP
Classifier: License :: OSI Approved :: MIT License
